ezfinpy/__init__.py
ezfinpy/pandas_patcher.py
ezfinpy/simulator.py
ezfinpy/stats.py
ezfinpy/utils.py
ezfinpy-0.1.7.dist-info/LICENSE.txt
ezfinpy-0.1.7.dist-info/METADATA
ezfinpy-0.1.7.dist-info/WHEEL
ezfinpy-0.1.7.dist-info/RECORD
