Metadata-Version: 2.1
Name: ezfinpy
Version: 0.1.7
Summary: 
Home-page: https://github.com/renanmoretto/ezfinpy
License: MIT
Author: renanmoretto
Author-email: himynameisrenan@outlook.com
Requires-Python: >=3.10
Classifier: License :: OSI Approved :: MIT License
Classifier: Programming Language :: Python :: 3
Classifier: Programming Language :: Python :: 3.10
Classifier: Programming Language :: Python :: 3.11
Requires-Dist: datetime (>=4.9)
Requires-Dist: matplotlib (>=3.6.0)
Requires-Dist: numpy (>=1.22.0)
Requires-Dist: pandas (>=1.5.0)
Project-URL: Repository, https://github.com/renanmoretto/ezfinpy
